ytproofreading/__init__.py
ytproofreading/ytproofreading.py
ytproofreading-1.4.dist-info/LICENSE
ytproofreading-1.4.dist-info/METADATA
ytproofreading-1.4.dist-info/WHEEL
ytproofreading-1.4.dist-info/top_level.txt
ytproofreading-1.4.dist-info/RECORD
