Metadata-Version: 2.1
Name: ytproofreading
Version: 1.4
Summary: A python module to use the proofreading support api of Yahoo! japan
Home-page: https://github.com/6ast1an979/ytproofreading
Author: 6ast1an979
Author-email: 6ast1an979@gmail.com
License: UNKNOWN
Platform: UNKNOWN
Classifier: Programming Language :: Python :: 3.8
Classifier: License :: OSI Approved :: MIT License
Classifier: Operating System :: OS Independent
